mypackage/__init__.py
mypackage/functions.py
mypackage/greet.py
mypackage-0495843/__init__.py
mypackage-0495843/functions.py
mypackage-0495843/greet.py
mypackage_0495843-111.111.0.dist-info/METADATA
mypackage_0495843-111.111.0.dist-info/WHEEL
mypackage_0495843-111.111.0.dist-info/top_level.txt
mypackage_0495843-111.111.0.dist-info/RECORD
