Metadata-Version: 2.1
Name: mypackage-0495843
Version: 111.111.0
Summary: Testing installation of Package
Home-page: UNKNOWN
Author: musheer
Author-email: musheeruddin@hotmail.com
License: UNKNOWN
Platform: UNKNOWN
